toml.py
toml-0.10.0.dist-info/top_level.txt
toml-0.10.0.dist-info/DESCRIPTION.rst
toml-0.10.0.dist-info/RECORD
toml-0.10.0.dist-info/LICENSE.txt
toml-0.10.0.dist-info/WHEEL
toml-0.10.0.dist-info/metadata.json
toml-0.10.0.dist-info/METADATA
toml/encoder.py
toml/__init__.py
toml/decoder.py
toml/tz.py
toml/ordered.py
